directus_py_sdk/__init__.py
directus_py_sdk/main.py
directus_sdk_py/__init__.py
directus_sdk_py/main.py
directus_sdk_py-1.1.0.dist-info/LICENSE.md
directus_sdk_py-1.1.0.dist-info/METADATA
directus_sdk_py-1.1.0.dist-info/WHEEL
directus_sdk_py-1.1.0.dist-info/entry_points.txt
directus_sdk_py-1.1.0.dist-info/top_level.txt
directus_sdk_py-1.1.0.dist-info/RECORD
