Metadata-Version: 2.1
Name: directus-sdk-py
Version: 1.1.0
Summary: Python SDK for interacting with Directus API (colletion, items, users, files)
Home-page: https://github.com/reise69/directus-py-sdk
Author: Alban Lamberet
Author-email: contact@refbax.com
License: MIT
Platform: UNKNOWN
Classifier: License :: OSI Approved :: MIT License
Classifier: Programming Language :: Python :: 3.7
Classifier: Programming Language :: Python :: 3.8
Classifier: Programming Language :: Python :: 3.9
Classifier: Programming Language :: Python :: 3.10
Requires-Dist: requests
Requires-Dist: sqlparse
Requires-Dist: urllib3
